Metadata-Version: 2.1
Name: aac-distributions
Version: 0.7
Summary: Gaussian and Binomial distributions
Home-page: UNKNOWN
Author: Alberto Armero
Author-email: alberto.armero86@gmail.com
License: UNKNOWN
Platform: UNKNOWN
Classifier: Programming Language :: Python :: 3
Classifier: License :: OSI Approved :: MIT License
Classifier: Operating System :: OS Independent
